{
  "main": {
    "id": "576bafc3b300f58a",
    "type": "split",
    "children": [
      {
        "id": "2c2050dbfe3bb14e",
        "type": "tabs",
        "children": [
          {
            "id": "afb456cb10a6951b",
            "type": "leaf",
            "state": {
              "type": "markdown",
              "state": {
                "file": "Tareas por hacer - Entrega 4 (Avance 1).md",
                "mode": "source",
                "source": false
              }
            }
          }
        ]
      }
    ],
    "direction": "vertical"
  },
  "left": {
    "id": "c8c3059d34bdb28c",
    "type": "split",
    "children": [
      {
        "id": "c78d6325c9840ebf",
        "type": "tabs",
        "children": [
          {
            "id": "ff499784e9cf3f38",
            "type": "leaf",
            "state": {
              "type": "file-explorer",
              "state": {
                "sortOrder": "alphabetical"
              }
            }
          },
          {
            "id": "6592ebbaeb4c5baf",
            "type": "leaf",
            "state": {
              "type": "search",
              "state": {
                "query": "",
                "matchingCase": false,
                "explainSearch": false,
                "collapseAll": false,
                "extraContext": false,
                "sortOrder": "alphabetical"
              }
            }
          },
          {
            "id": "f8f2173bc0347699",
            "type": "leaf",
            "state": {
              "type": "bookmarks",
              "state": {}
            }
          }
        ]
      }
    ],
    "direction": "horizontal",
    "width": 300
  },
  "right": {
    "id": "15cdc3ee74690433",
    "type": "split",
    "children": [
      {
        "id": "5eac58ed4ee0dbfc",
        "type": "tabs",
        "children": [
          {
            "id": "663fff0a4110047f",
            "type": "leaf",
            "state": {
              "type": "backlink",
              "state": {
                "file": "Tareas por hacer - Entrega 4 (Avance 1).md",
                "collapseAll": false,
                "extraContext": false,
                "sortOrder": "alphabetical",
                "showSearch": false,
                "searchQuery": "",
                "backlinkCollapsed": false,
                "unlinkedCollapsed": true
              }
            }
          },
          {
            "id": "d1777272445e304d",
            "type": "leaf",
            "state": {
              "type": "outgoing-link",
              "state": {
                "file": "Tareas por hacer - Entrega 4 (Avance 1).md",
                "linksCollapsed": false,
                "unlinkedCollapsed": true
              }
            }
          },
          {
            "id": "20f4b79d46bd2677",
            "type": "leaf",
            "state": {
              "type": "tag",
              "state": {
                "sortOrder": "frequency",
                "useHierarchy": true
              }
            }
          },
          {
            "id": "639937cac747bd54",
            "type": "leaf",
            "state": {
              "type": "outline",
              "state": {
                "file": "Tareas por hacer - Entrega 4 (Avance 1).md"
              }
            }
          }
        ]
      }
    ],
    "direction": "horizontal",
    "width": 300,
    "collapsed": true
  },
  "left-ribbon": {
    "hiddenItems": {
      "switcher:Abrir selector rápido": false,
      "graph:Abrir vista gráfica": false,
      "canvas:Crear nuevo lienzo": false,
      "daily-notes:Abrir la nota de hoy": false,
      "templates:Insertar plantilla": false,
      "command-palette:Abrir paleta de comandos": false
    }
  },
  "active": "afb456cb10a6951b",
  "lastOpenFiles": [
    "20-08-2024 revisión 3.md",
    "Tareas por hacer - Entrega 4 (Avance 1).md",
    "Tareas por hacer - Entrega 3.md",
    "13-08-2024 revisión 2.md",
    "Bitácora General.md",
    "Tareas por hacer - Entrega 2.md",
    "Tareas por hacer.md",
    "30-07-2024 revisión 1.md",
    "Bienvenido.md"
  ]
}